{"cameraMode":{"drawMode":0,"name":"Shaded","section":"Shading Mode"},"sceneLighting":true,"audioPlay":false,"sceneViewState":{"m_AlwaysRefresh":false,"showFog":true,"showSkybox":true,"showFlares":true,"showImageEffects":true,"showParticleSystems":true,"showVisualEffectGraphs":true,"m_FxEnabled":true},"in2DMode":false,"pivot":{"x":0.0,"y":12.770000457763672,"z":-23.75},"rotation":{"x":0.05739624425768852,"y":0.7399027943611145,"z":-0.06364678591489792,"w":0.667234480381012},"size":12.12435531616211,"orthographic":false}